LICENSE.txt
MANIFEST.in
README.rst
setup.py
kickass/__init__.py
kickass/command_line.py
kickass/data.py
kickass/kickass_parse.py
kickass/network.py
kickass/printer.py
kickass/torrent.py
kickass_get.egg-info/PKG-INFO
kickass_get.egg-info/SOURCES.txt
kickass_get.egg-info/dependency_links.txt
kickass_get.egg-info/entry_points.txt
kickass_get.egg-info/requires.txt
kickass_get.egg-info/top_level.txt