Metadata-Version: 1.1
Name: kickass-get
Version: 0.2.2
Summary: A command-line interface for kat.cr (Kickass Torrents)
Home-page: https://github.com/jingnanshi/kickass-get
Author: Jingnan Shi
Author-email: jshi@g.hmc.edu
License: MIT
Keywords: torrent,magnet,download,kickass,kat,client
Platform: UNKNOWN
Classifier: Development Status :: 3 - Alpha
Classifier: Topic :: Utilities
Classifier: Topic :: Terminals
Classifier: Topic :: System :: Networking
Classifier: Programming Language :: Python :: 2 :: Only
Classifier: Programming Language :: Python :: 2.7
Classifier: License :: OSI Approved :: MIT License
